challenge_welding/__init__.py
challenge_welding/_version_.py
challenge_welding/ai_component_interface.py
challenge_welding/dataloaders.py
challenge_welding/inference_tools.py
challenge_welding/user_interface.py
challenge_welding-1.0.dist-info/METADATA
challenge_welding-1.0.dist-info/WHEEL
challenge_welding-1.0.dist-info/licenses/LICENSE
challenge_welding-1.0.dist-info/RECORD
