Metadata-Version: 2.4
Name: challenge-welding
Version: 1.0
Dynamic: Requires-Dist
Summary: Set of tools functions to help challenge Welding users to interacts with challenge datasets
License-Expression: MPL-2.0
License-File: LICENSE
Requires-Python: >=3.12
